Metadata-Version: 2.1
Name: finx-io-sandbox
Version: 0.0.5
Summary: Python client for FinX Platform APIs
Author-email: FinX Capital Markets LLC <support@finx.io>
License: GNU AFFERO GENERAL PUBLIC LICENSE
Project-URL: Homepage, https://github.com/FinX-IO/finx
Project-URL: Bug Tracker, https://github.com/FinX-IO/finx/issues
Classifier: Programming Language :: Python :: 3
Classifier: Operating System :: OS Independent
Requires-Python: >=3.10
License-File: LICENSE
Requires-Dist: aiohttp
Requires-Dist: nest-asyncio
Requires-Dist: numpy
Requires-Dist: pandas
Requires-Dist: plotly
Requires-Dist: pytest
Requires-Dist: requests
Requires-Dist: scipy
Requires-Dist: websocket-client
Requires-Dist: websockets
